raas/__init__.py
raas/api_helper.py
raas/configuration.py
raas/decorators.py
raas/raas_client.py
raas/controllers/__init__.py
raas/controllers/accounts_controller.py
raas/controllers/base_controller.py
raas/controllers/catalog_controller.py
raas/controllers/customers_controller.py
raas/controllers/exchange_rates_controller.py
raas/controllers/fund_controller.py
raas/controllers/orders_controller.py
raas/controllers/status_controller.py
raas/exceptions/__init__.py
raas/exceptions/api_exception.py
raas/exceptions/raas_client_exception.py
raas/exceptions/raas_generic_exception.py
raas/exceptions/raas_server_exception.py
raas/http/__init__.py
raas/http/http_call_back.py
raas/http/http_client.py
raas/http/http_context.py
raas/http/http_method_enum.py
raas/http/http_request.py
raas/http/http_response.py
raas/http/requests_client.py
raas/http/auth/__init__.py
raas/http/auth/basic_auth.py
raas/models/__init__.py
raas/models/account_model.py
raas/models/account_summary_model.py
raas/models/billing_address_model.py
raas/models/brand_model.py
raas/models/catalog_model.py
raas/models/create_account_request_model.py
raas/models/create_credit_card_request_model.py
raas/models/create_customer_request_model.py
raas/models/create_order_request_model.py
raas/models/credit_card_model.py
raas/models/currency_breakdown_model.py
raas/models/customer_model.py
raas/models/deposit_request_model.py
raas/models/deposit_response_model.py
raas/models/exchange_rate_model.py
raas/models/exchange_rate_response_model.py
raas/models/full_name_email_model.py
raas/models/get_deposit_response_model.py
raas/models/get_orders_response_model.py
raas/models/item_model.py
raas/models/name_email_model.py
raas/models/new_credit_card_model.py
raas/models/order_model.py
raas/models/order_summary_model.py
raas/models/page_model.py
raas/models/raas_client_error_model.py
raas/models/raas_server_error_model.py
raas/models/resend_order_response_model.py
raas-2.2.0.dist-info/DESCRIPTION.rst
raas-2.2.0.dist-info/METADATA
raas-2.2.0.dist-info/RECORD
raas-2.2.0.dist-info/WHEEL
raas-2.2.0.dist-info/metadata.json
raas-2.2.0.dist-info/top_level.txt
