Metadata-Version: 2.0
Name: raas
Version: 2.2.0
Summary: With this RESTful API you can integrate a global reward or incentive program into your app or platform. If you have any questions or if you'd like to receive your own credentials, please contact us at devsupport@tangocard.com.
Home-page: https://apimatic.io/
Author: APIMatic SDK Generator
Author-email: support@apimatic.io
License: UNKNOWN
Platform: UNKNOWN
Requires-Dist: requests (<3.0,>=2.9.1)
Requires-Dist: jsonpickle (<1.0,>=0.7.1)
Requires-Dist: cachecontrol (<1.0,>=0.11.7)
Requires-Dist: python-dateutil (<3.0,>=2.5.3)
